{
    "dataroot": "lolol",
    "batchSize": 1,
    "loadSize": 288,
    "fineSize": 256,
    "input_nc": 3,
    "output_nc": 3,
    "ngf": 64,
    "ndf": 64,
    "which_model_netD": "basic",
    "which_model_netG": "resnet_9blocks",
    "n_layers_D": 3,
    "gpu_ids": [
        0
    ],
    "name": "experiment_name",
    "dataset_mode": "unaligned",
    "model": "gc_gan_share",
    "which_direction": "AtoB",
    "nThreads": 1,
    "checkpoints_dir": "./checkpoints",
    "norm": "instance",
    "serial_batches": false,
    "display_winsize": 256,
    "display_id": 0,
    "display_port": 8097,
    "no_dropout": false,
    "max_dataset_size": Infinity,
    "resize_or_crop": "resize",
    "no_flip": true,
    "init_type": "xavier",
    "ntest": Infinity,
    "results_dir": "./results/",
    "aspect_ratio": 1.0,
    "phase": "test",
    "which_epoch": "latest",
    "how_many": 50,
    "geometry": "rot",
    "isTrain": false
}